tiny_diff-0.1.0.dist-info/METADATA
tiny_diff-0.1.0.dist-info/WHEEL
tiny_diff/__init__.py
tiny_diff/__version__.py
tiny_diff/constants.py
tiny_diff/losses/__init__.py
tiny_diff/losses/discriminator/__init__.py
tiny_diff/losses/discriminator/d_loss.py
tiny_diff/losses/discriminator/hinge.py
tiny_diff/losses/discriminator/vanilla.py
tiny_diff/losses/normal.py
tiny_diff/losses/vae_loss.py
tiny_diff/models/__init__.py
tiny_diff/models/conv_model.py
tiny_diff/models/discriminator.py
tiny_diff/models/unet/__init__.py
tiny_diff/models/unet/layers.py
tiny_diff/models/unet/model.py
tiny_diff/models/unet/wrappers.py
tiny_diff/models/vae/__init__.py
tiny_diff/models/vae/components.py
tiny_diff/models/vae/gan.py
tiny_diff/models/vae/layers.py
tiny_diff/models/vae/model.py
tiny_diff/modules/__init__.py
tiny_diff/modules/attention.py
tiny_diff/modules/conv.py
tiny_diff/modules/layer_factory.py
tiny_diff/modules/nonlinearity.py
tiny_diff/modules/norm.py
tiny_diff/modules/resampling.py
tiny_diff/modules/residual/__init__.py
tiny_diff/modules/residual/blocks.py
tiny_diff/modules/residual/layers.py
tiny_diff/schedulers/__init__.py
tiny_diff/schedulers/ddpm.py
tiny_diff/utils.py
tiny_diff/version.info
tiny_diff-0.1.0.dist-info/RECORD
