Metadata-Version: 2.1
Name: tiny-diff
Version: 0.1.0
Summary: Hackable implementation of diffusion models
Author-Email: =?utf-8?q?Alejandro_Bar=C3=B3n?= <alejandrobarongarcia10@gmail.com>
License: MIT
Requires-Python: >=3.9
Requires-Dist: torch<2.4,>=2
